{
	"info": {
		"_postman_id": "adab4b9d-f91d-4e3c-add3-67654316ad7e",
		"name": "CMS",
		"schema": "https://schema.getpostman.com/json/collection/v2.0.0/collection.json",
		"_exporter_id": "27196053"
	},
	"item": [
		{
			"name": "Categories",
			"item": [
				{
					"name": "categories",
					"request": {
						"auth": {
							"type": "bearer",
							"bearer": {
								"token": "{{token}}"
							}
						},
						"method": "GET",
						"header": [],
						"url": "{{Base_Url}}/api/categories/index"
					},
					"response": []
				},
				{
					"name": "store",
					"request": {
						"auth": {
							"type": "bearer",
							"bearer": {
								"token": "{{token}}"
							}
						},
						"method": "POST",
						"header": [],
						"body": {
							"mode": "formdata",
							"formdata": [
								{
									"key": "name",
									"value": "Mern",
									"type": "text"
								}
							]
						},
						"url": "{{Base_Url}}/api/categories/store"
					},
					"response": []
				},
				{
					"name": "edit",
					"protocolProfileBehavior": {
						"disableBodyPruning": true
					},
					"request": {
						"auth": {
							"type": "bearer",
							"bearer": {
								"token": "{{token}}"
							}
						},
						"method": "GET",
						"header": [],
						"body": {
							"mode": "formdata",
							"formdata": [
								{
									"key": "id",
									"value": "",
									"type": "text",
									"disabled": true
								}
							]
						},
						"url": {
							"raw": "{{Base_Url}}/api/categories/edit?id=1",
							"host": [
								"{{Base_Url}}"
							],
							"path": [
								"api",
								"categories",
								"edit"
							],
							"query": [
								{
									"key": "id",
									"value": "1"
								}
							]
						}
					},
					"response": []
				},
				{
					"name": "update",
					"request": {
						"auth": {
							"type": "bearer",
							"bearer": {
								"token": "{{token}}"
							}
						},
						"method": "POST",
						"header": [],
						"body": {
							"mode": "formdata",
							"formdata": [
								{
									"key": "name",
									"value": "Technology",
									"type": "text"
								}
							]
						},
						"url": {
							"raw": "{{Base_Url}}/api/categories/update?id=1",
							"host": [
								"{{Base_Url}}"
							],
							"path": [
								"api",
								"categories",
								"update"
							],
							"query": [
								{
									"key": "id",
									"value": "1"
								}
							]
						}
					},
					"response": []
				},
				{
					"name": "delete",
					"request": {
						"auth": {
							"type": "bearer",
							"bearer": {
								"token": "{{token}}"
							}
						},
						"method": "POST",
						"header": [],
						"url": {
							"raw": "{{Base_Url}}/api/categories/delete?id=5",
							"host": [
								"{{Base_Url}}"
							],
							"path": [
								"api",
								"categories",
								"delete"
							],
							"query": [
								{
									"key": "id",
									"value": "5"
								}
							]
						}
					},
					"response": []
				}
			]
		},
		{
			"name": "Articles",
			"item": [
				{
					"name": "index",
					"request": {
						"auth": {
							"type": "bearer",
							"bearer": {
								"token": "{{token}}"
							}
						},
						"method": "GET",
						"header": [],
						"url": "{{Base_Url}}/api/articles/index"
					},
					"response": []
				},
				{
					"name": "create",
					"request": {
						"auth": {
							"type": "bearer",
							"bearer": {
								"token": "{{token}}"
							}
						},
						"method": "POST",
						"header": [],
						"body": {
							"mode": "raw",
							"raw": "{\r\n    \"categories\": [6,7],\r\n    \"title\": \"Fullstack dev\",\r\n    \"content\": \"test content\",\r\n    \"published_at\": \"20/12/2023\"\r\n}",
							"options": {
								"raw": {
									"language": "json"
								}
							}
						},
						"url": "{{Base_Url}}/api/articles/store"
					},
					"response": []
				},
				{
					"name": "Update",
					"request": {
						"auth": {
							"type": "bearer",
							"bearer": {
								"token": "{{token}}"
							}
						},
						"method": "POST",
						"header": [],
						"body": {
							"mode": "raw",
							"raw": "{\r\n    \"categories\": [4,5],\r\n    \"title\": \"Mern development\",\r\n    \"content\": \"test content\",\r\n    \"published_at\": \"20/12/2023\"\r\n}",
							"options": {
								"raw": {
									"language": "json"
								}
							}
						},
						"url": {
							"raw": "{{Base_Url}}/api/articles/update?id=3",
							"host": [
								"{{Base_Url}}"
							],
							"path": [
								"api",
								"articles",
								"update"
							],
							"query": [
								{
									"key": "id",
									"value": "3"
								}
							]
						}
					},
					"response": []
				},
				{
					"name": "delete",
					"request": {
						"auth": {
							"type": "bearer",
							"bearer": {
								"token": "{{token}}"
							}
						},
						"method": "POST",
						"header": [],
						"url": {
							"raw": "{{Base_Url}}/api/articles/delete?id=4",
							"host": [
								"{{Base_Url}}"
							],
							"path": [
								"api",
								"articles",
								"delete"
							],
							"query": [
								{
									"key": "id",
									"value": "4"
								}
							]
						}
					},
					"response": []
				},
				{
					"name": "Category-Article",
					"request": {
						"auth": {
							"type": "bearer",
							"bearer": {
								"token": "{{token}}"
							}
						},
						"method": "GET",
						"header": [],
						"url": {
							"raw": "http://127.0.0.1:8000/api/articles/category?id=3",
							"protocol": "http",
							"host": [
								"127",
								"0",
								"0",
								"1"
							],
							"port": "8000",
							"path": [
								"api",
								"articles",
								"category"
							],
							"query": [
								{
									"key": "id",
									"value": "3"
								}
							]
						}
					},
					"response": []
				},
				{
					"name": "Article-by -slug",
					"request": {
						"auth": {
							"type": "bearer",
							"bearer": {
								"token": "{{token}}"
							}
						},
						"method": "GET",
						"header": [],
						"url": {
							"raw": "http://127.0.0.1:8000/api/articles/slug?slug=development-process",
							"protocol": "http",
							"host": [
								"127",
								"0",
								"0",
								"1"
							],
							"port": "8000",
							"path": [
								"api",
								"articles",
								"slug"
							],
							"query": [
								{
									"key": "slug",
									"value": "development-process"
								}
							]
						}
					},
					"response": []
				},
				{
					"name": "Article-by-User",
					"request": {
						"auth": {
							"type": "bearer",
							"bearer": {
								"token": "{{token}}"
							}
						},
						"method": "GET",
						"header": [],
						"url": {
							"raw": "http://127.0.0.1:8000/api/articles/user",
							"protocol": "http",
							"host": [
								"127",
								"0",
								"0",
								"1"
							],
							"port": "8000",
							"path": [
								"api",
								"articles",
								"user"
							],
							"query": [
								{
									"key": "",
									"value": "-process",
									"disabled": true
								}
							]
						}
					},
					"response": []
				}
			]
		},
		{
			"name": "register",
			"request": {
				"method": "POST",
				"header": [],
				"body": {
					"mode": "formdata",
					"formdata": [
						{
							"key": "name",
							"value": "Amirul Islam",
							"type": "text"
						},
						{
							"key": "email",
							"value": "amiru2@admin.com",
							"type": "text"
						},
						{
							"key": "password",
							"value": "12345678",
							"type": "text"
						},
						{
							"key": "password_confirmation",
							"value": "12345678",
							"type": "text"
						}
					]
				},
				"url": "{{Base_Url}}/api/auth/register"
			},
			"response": []
		},
		{
			"name": "login",
			"request": {
				"method": "POST",
				"header": [],
				"body": {
					"mode": "formdata",
					"formdata": [
						{
							"key": "email",
							"value": "admin@admin.com",
							"type": "text"
						},
						{
							"key": "password",
							"value": "12345678",
							"type": "text"
						}
					]
				},
				"url": "http://127.0.0.1:8000/api/auth/login"
			},
			"response": []
		},
		{
			"name": "logout",
			"request": {
				"auth": {
					"type": "bearer",
					"bearer": {
						"token": "{{token}}"
					}
				},
				"method": "POST",
				"header": [
					{
						"key": "Accept",
						"value": "application/ecmascript",
						"type": "text"
					},
					{
						"key": "Content-Type",
						"value": "application/ecmascript",
						"type": "text"
					}
				],
				"url": "http://127.0.0.1:8000/api/auth/logout"
			},
			"response": []
		},
		{
			"name": "profile",
			"request": {
				"auth": {
					"type": "bearer",
					"bearer": {
						"token": "{{token}}"
					}
				},
				"method": "GET",
				"header": [],
				"url": "http://127.0.0.1:8000/api/auth/user-profile"
			},
			"response": []
		}
	],
	"event": [
		{
			"listen": "prerequest",
			"script": {
				"type": "text/javascript",
				"exec": [
					""
				]
			}
		},
		{
			"listen": "test",
			"script": {
				"type": "text/javascript",
				"exec": [
					""
				]
			}
		}
	],
	"variable": [
		{
			"key": "Base_Url",
			"value": "http://127.0.0.1:8000",
			"type": "string"
		},
		{
			"key": "token",
			"value": "eyJ0eXAiOiJKV1QiLCJhbGciOiJIUzI1NiJ9.eyJpc3MiOiJodHRwOi8vMTI3LjAuMC4xOjgwMDAvYXBpL2F1dGgvbG9naW4iLCJpYXQiOjE3MDMwNDE3OTAsImV4cCI6MTcwMzA0NTM5MCwibmJmIjoxNzAzMDQxNzkwLCJqdGkiOiI1R3dEdjVra2lxRnp6aFBKIiwic3ViIjoiMSIsInBydiI6IjIzYmQ1Yzg5NDlmNjAwYWRiMzllNzAxYzQwMDg3MmRiN2E1OTc2ZjcifQ.cJoE0XcyroFBuj_b23XwPPGSlpnfCsOpR4LIa0UYJDk",
			"type": "string"
		}
	]
}